paramflow/__init__.py
paramflow/convert.py
paramflow/frozen.py
paramflow/params.py
paramflow/parser.py
paramflow-0.5.6.dist-info/licenses/LICENSE
paramflow-0.5.6.dist-info/METADATA
paramflow-0.5.6.dist-info/WHEEL
paramflow-0.5.6.dist-info/top_level.txt
paramflow-0.5.6.dist-info/RECORD
