Metadata-Version: 2.4
Name: paramflow
Version: 0.5.6
Summary: A lightweight library for hyperparameter and configuration management
Home-page: https://github.com/mduszyk/paramflow
Classifier: Programming Language :: Python :: 3
Classifier: License :: OSI Approved :: MIT License
License-File: LICENSE
Requires-Dist: pyyaml
Provides-Extra: dotenv
Requires-Dist: python-dotenv; extra == "dotenv"
Dynamic: classifier
Dynamic: description
Dynamic: description-content-type
Dynamic: home-page
Dynamic: license-file
Dynamic: provides-extra
Dynamic: requires-dist
Dynamic: summary
